akrophonobolos/__init__.py
akrophonobolos/__version__.py
akrophonobolos/akrophonobolos.py
akrophonobolos/logistes.py
akrophonobolos/obol.py
tests/__init__.py
tests/test_class.py
tests/test_functions.py
tests/test_inscriptions.py
akrophonobolos-1.0.0.dist-info/LICENSE
akrophonobolos-1.0.0.dist-info/METADATA
akrophonobolos-1.0.0.dist-info/WHEEL
akrophonobolos-1.0.0.dist-info/entry_points.txt
akrophonobolos-1.0.0.dist-info/top_level.txt
akrophonobolos-1.0.0.dist-info/RECORD
