Metadata-Version: 2.1
Name: akrophonobolos
Version: 1.0.0
Summary: Ancient Athenian acrophonic numeral converter
Home-page: https://github.com/seanredmond/Akrophonobolos
Author: Sean Redmond
Author-email: github-smr@sneakemail.com
Project-URL: Bug Tracker, https://github.com/seanredmond/Akrophonobolos/issues
Classifier: Programming Language :: Python :: 3
Classifier: License :: OSI Approved :: GNU General Public License v3 or later (GPLv3+)
Classifier: Operating System :: OS Independent
Requires-Python: >=3.8
License-File: LICENSE
